CHANGES.rst
MANIFEST.in
README.rst
setup.cfg
setup.py
redis_shard/__init__.py
redis_shard/_compat.py
redis_shard/commands.py
redis_shard/hashring.py
redis_shard/helpers.py
redis_shard/pipeline.py
redis_shard/sentinel.py
redis_shard/shard.py
redis_shard/url.py
redis_shard.egg-info/PKG-INFO
redis_shard.egg-info/SOURCES.txt
redis_shard.egg-info/dependency_links.txt
redis_shard.egg-info/not-zip-safe
redis_shard.egg-info/requires.txt
redis_shard.egg-info/top_level.txt